pweb_orm/__init__.py
pweb_orm/common/__init__.py
pweb_orm/common/pweb_orm_cli.py
pweb_orm/common/pweb_orm_exception.py
pweb_orm/common/pweb_orm_util.py
pweb_orm/common/pweb_saas_context.py
pweb_orm/model/__init__.py
pweb_orm/model/pweb_model.py
pweb_orm/model/pweb_orm_model.py
pweb_orm/orm/__init__.py
pweb_orm/orm/pweb_orm.py
pweb_orm/orm/pweb_orm_session.py
pweb_orm/orm/pweb_saas.py
pweb_orm/query/__init__.py
pweb_orm/query/pweb_db_query_helper.py
pweb_orm/query/pweb_query_suggestion.py
pweb_orm-0.0.8.dist-info/LICENSE
pweb_orm-0.0.8.dist-info/METADATA
pweb_orm-0.0.8.dist-info/WHEEL
pweb_orm-0.0.8.dist-info/top_level.txt
pweb_orm-0.0.8.dist-info/RECORD
