Metadata-Version: 2.1
Name: pweb-orm
Version: 0.0.8
Summary: PWeb Object Relational Mapping Library, based on SQLAlchemy is an open-source SQL toolkit and object-relational mapper. It also used the Flask-SQLAlchemy extension.
Home-page: https://github.com/banglafighter/pweb-orm
Author: Bangla Fighter
Author-email: banglafighter.com@gmail.com
License: Apache 2.0
Platform: any
Classifier: Intended Audience :: Developers
Classifier: License :: OSI Approved :: Apache Software License
Classifier: Programming Language :: Python
License-File: LICENSE
Requires-Dist: Flask-SQLAlchemy ==3.1.1
Requires-Dist: ppy-common
